ghostops/__init__.py
ghostops/__main__.py
ghostops/core.py
ghostops/ghostops.py
ghostops/utils.py
ghostops-0.1.0.dist-info/LICENSE
ghostops-0.1.0.dist-info/METADATA
ghostops-0.1.0.dist-info/WHEEL
ghostops-0.1.0.dist-info/entry_points.txt
ghostops-0.1.0.dist-info/top_level.txt
ghostops-0.1.0.dist-info/RECORD
