Metadata-Version: 2.1
Name: ghostops
Version: 0.1.0
Summary: A powerful Command and Control Framework for penetration testing.
Home-page: https://github.com/4w4647/ghostops
Author: Awagat Dhungana
Author-email: 4w4647@gmail.com
License: BSD-3-Clause
Classifier: Development Status :: 3 - Alpha
Classifier: Environment :: Console
Classifier: Intended Audience :: Information Technology
Classifier: License :: OSI Approved :: BSD License
Classifier: Operating System :: POSIX :: Linux
Classifier: Programming Language :: Python :: 3
Classifier: Topic :: Security
Requires-Python: >=3.6
License-File: LICENSE
